inquirer_rhy/__init__.py
inquirer_rhy/color_print.py
inquirer_rhy/prompt.py
inquirer_rhy/prompts/__init__.py
inquirer_rhy/prompts/checkbox.py
inquirer_rhy/prompts/common.py
inquirer_rhy/prompts/confirm.py
inquirer_rhy/prompts/editor.py
inquirer_rhy/prompts/expand.py
inquirer_rhy/prompts/input.py
inquirer_rhy/prompts/list.py
inquirer_rhy/prompts/password.py
inquirer_rhy/prompts/rawlist.py
inquirer_rhy/separator.py
inquirer_rhy/utils.py
inquirer_rhy-0.1.3.dist-info/METADATA
inquirer_rhy-0.1.3.dist-info/WHEEL
inquirer_rhy-0.1.3.dist-info/RECORD
